TFDWT/DWTIDWT1Dv1.py
TFDWT/DWTIDWT2Dv1.py
TFDWT/GETDWTFiltersOrtho.py
TFDWT/__init__.py
TFDWT/dbFBimpulseResponse.py
TFDWT/get_A_matrix_dwt_analysisFB_unit.py
tfdwt-0.1.0.dist-info/METADATA
tfdwt-0.1.0.dist-info/WHEEL
tfdwt-0.1.0.dist-info/licenses/LICENSE
tfdwt-0.1.0.dist-info/RECORD
