Metadata-Version: 2.4
Name: TFDWT
Version: 0.1.0
Summary: Fast Discrete Wavelet Transform TensorFlow Layers
Project-URL: Homepage, https://github.com/kkt-ee/TFDWT
Project-URL: Issues, https://github.com/kkt-ee/TFDWT/issues
Author-email: Kishore Kumar Tarafdar <kishorektarafdar@gmail.com>
License-Expression: GPL-3.0-or-later
License-File: LICENSE
Classifier: Intended Audience :: Science/Research
Classifier: Operating System :: OS Independent
Classifier: Programming Language :: Python :: 3
Classifier: Topic :: Scientific/Engineering
Requires-Python: >=3.9
